cpa_std
