Metadata-Version: 2.1
Name: cpa-std
Version: 0.3
Summary: 根据企业会计准则规范会计科目名称
Home-page: https://github.com/wangmarkqi/cpa_std
Author: Wang Qi
Author-email: wangmarkqi@gmail.com
License: UNKNOWN
Keywords: 会计,科目,规范
Platform: UNKNOWN
Classifier: Programming Language :: Python :: 3
Classifier: License :: OSI Approved :: MIT License
Classifier: Operating System :: OS Independent
Requires-Python: >=3.6
